locater/__init__.py
locater/functions.py
locater/locator.py
pyfindimage-0.25.dist-info/METADATA
pyfindimage-0.25.dist-info/WHEEL
pyfindimage-0.25.dist-info/top_level.txt
pyfindimage-0.25.dist-info/RECORD
