Metadata-Version: 2.1
Name: pyfindimage
Version: 0.25
Summary: Image finder based on text
Home-page: 
Author: lewis
Author-email: lewis.morris@gmail.com
License: MIT
